adjugate.py
adjugate-0.9.3.dist-info/LICENSE
adjugate-0.9.3.dist-info/METADATA
adjugate-0.9.3.dist-info/WHEEL
adjugate-0.9.3.dist-info/top_level.txt
adjugate-0.9.3.dist-info/RECORD
